ocrd_detectron2/__init__.py
ocrd_detectron2/cli.py
ocrd_detectron2/config.py
ocrd_detectron2/ocrd-tool.json
ocrd_detectron2/presets_DocBank_X101.json
ocrd_detectron2/presets_DocBank_X101_page.json
ocrd_detectron2/presets_Jambo-sudo_X101.json
ocrd_detectron2/presets_Math_R50.json
ocrd_detectron2/presets_NewspaperNavigator_R50.json
ocrd_detectron2/presets_PRImALayout_R50.json
ocrd_detectron2/presets_PubLayNet_R101.json
ocrd_detectron2/presets_PubLayNet_R101_JPLeoRX.json
ocrd_detectron2/presets_PubLayNet_R50.json
ocrd_detectron2/presets_PubLayNet_R50_JPLeoRX.json
ocrd_detectron2/presets_PubLayNet_X101.json
ocrd_detectron2/presets_TableBank_X152.json
ocrd_detectron2/presets_TableBank_X152_Psarpei.json
ocrd_detectron2/segment.py
ocrd_detectron2-0.1.8.dist-info/METADATA
ocrd_detectron2-0.1.8.dist-info/WHEEL
ocrd_detectron2-0.1.8.dist-info/dependency_links.txt
ocrd_detectron2-0.1.8.dist-info/entry_points.txt
ocrd_detectron2-0.1.8.dist-info/top_level.txt
ocrd_detectron2-0.1.8.dist-info/RECORD
