Metadata-Version: 2.1
Name: ocrd-detectron2
Version: 0.1.8
Summary: OCR-D wrapper for detectron2 based segmentation models
Home-page: https://github.com/bertsky/ocrd_detectron2
Author: Robert Sachunsky, Julian Balling
Author-email: sachunsky@informatik.uni-leipzig.de, balling@infai.org
License: MIT
Requires-Dist: ocrd (>=2.40)
Requires-Dist: click (>=7.0)
Requires-Dist: scipy
Requires-Dist: numpy (>=1.17.0)
Requires-Dist: pillow (>=7.1.2)
Requires-Dist: shapely
Requires-Dist: scikit-image (>=0.17.2)
Requires-Dist: typing-extensions
Requires-Dist: torch (>=1.10.0)
Requires-Dist: torchvision (>=0.11.2)
Requires-Dist: detectron2 (>=0.6)
Requires-Dist: wheel
Requires-Dist: pycocotools
